{
  "nav.explore": "Clubs erkunden",
  "nav.blog": "Blog",
  "nav.dashboard": "Club-Panel",
  "nav.logout": "Abmelden",
  "home.hero.title": "Entdecken Sie die Besten",
  "home.hero.subtitle": "Wir verbinden verantwortungsbewusste Cannabis-Communities in Spanien.",
  "home.hero.explore_clubs": "Clubs erkunden",
  "clubs.title": "Verzeichnis sozialer Clubs",
  "clubs.subtitle": "Entdecken Sie verifizierte Cannabis-Social-Clubs in ganz Spanien",
  "blog.title": "Cannabis-Blog",
  "footer.description": "Die führende Plattform zur Entdeckung und Verbindung mit Cannabis-Social-Clubs in Spanien.",
  "common.loading": "Laden...",
  "common.error": "Fehler",
  "common.success": "Erfolg"
}
